{
  "id": "ncu",
  "school": "國立中央大學",
  "name": "中央大學 14 節制",
  "periods": [
    {
      "id": "1",
      "startTime": "08:00",
      "endTime": "08:50"
    },
    {
      "id": "2",
      "startTime": "09:00",
      "endTime": "09:50"
    },
    {
      "id": "3",
      "startTime": "10:00",
      "endTime": "10:50"
    },
    {
      "id": "4",
      "startTime": "11:00",
      "endTime": "11:50"
    },
    {
      "id": "Z",
      "startTime": "12:00",
      "endTime": "12:50"
    },
    {
      "id": "5",
      "startTime": "13:00",
      "endTime": "13:50"
    },
    {
      "id": "6",
      "startTime": "14:00",
      "endTime": "14:50"
    },
    {
      "id": "7",
      "startTime": "15:00",
      "endTime": "15:50"
    },
    {
      "id": "8",
      "startTime": "16:00",
      "endTime": "16:50"
    },
    {
      "id": "9",
      "startTime": "17:00",
      "endTime": "17:50"
    },
    {
      "id": "A",
      "startTime": "18:00",
      "endTime": "18:50"
    },
    {
      "id": "B",
      "startTime": "19:00",
      "endTime": "19:50"
    },
    {
      "id": "C",
      "startTime": "20:00",
      "endTime": "20:50"
    },
    {
      "id": "D",
      "startTime": "21:00",
      "endTime": "21:50"
    }
  ]
}
